setup.py
digg2/gate.py
digg2/minimize.py
digg2/sequential.py
digg2.egg-info/PKG-INFO
digg2.egg-info/SOURCES.txt
digg2.egg-info/dependency_links.txt
digg2.egg-info/top_level.txt