Metadata-Version: 1.1
Name: digg2
Version: 0.1
Summary: Digital simulation library!
Home-page: https://github.com/khanstark
Author: Kaif Khan
Author-email: kaifkhan.khan0@gmail.com
License: MIT
Keywords: digital
Platform: UNKNOWN
Classifier: Development Status :: 4 - Beta
Classifier: Intended Audience :: Developers
Classifier: Topic :: Software Development :: Build Tools
Classifier: License :: OSI Approved :: MIT License
Classifier: Programming Language :: Python :: 3
Classifier: Programming Language :: Python :: 2
